PyMisc/__init__.py
PyMisc/pymisc.py
PyMisc/test.py
pymsc-0.0.1.dist-info/LICENSE
pymsc-0.0.1.dist-info/METADATA
pymsc-0.0.1.dist-info/WHEEL
pymsc-0.0.1.dist-info/top_level.txt
pymsc-0.0.1.dist-info/RECORD
