Metadata-Version: 2.1
Name: pymsc
Version: 0.0.1
Summary: Python Misc Tools Library
Home-page: http://bakerman.rf.gd
Author: Xcoder_1 (Pomen Gtasa)
Author-email: <mail@progamedev12.com>
License: UNKNOWN
Keywords: python,misc,tools
Platform: UNKNOWN
Classifier: Development Status :: 1 - Planning
Classifier: Intended Audience :: Developers
Classifier: Programming Language :: Python :: 3
Classifier: Operating System :: Unix
Classifier: Operating System :: MacOS :: MacOS X
Classifier: Operating System :: Microsoft :: Windows
License-File: LICENSE
Requires-Dist: pyfiglet
